{"cameraMode":{"drawMode":0,"name":"Shaded","section":"Shading Mode"},"sceneLighting":true,"audioPlay":false,"sceneViewState":{"m_AlwaysRefresh":false,"showFog":true,"showSkybox":true,"showFlares":true,"showImageEffects":true,"showParticleSystems":true,"showVisualEffectGraphs":true,"m_FxEnabled":true},"in2DMode":false,"pivot":{"x":6.310946941375732,"y":-4.997769832611084,"z":-0.011567751877009869},"rotation":{"x":-0.19119314849376679,"y":-0.6858171820640564,"z":0.1943160444498062,"w":-0.6747937798500061},"size":10.0,"orthographic":false}